{
    "fluentMethods": true,
    "clientRootFolder": "",
    "relationships": [
        {
            "relationshipName": "user",
            "otherEntityName": "user",
            "relationshipType": "many-to-one",
            "otherEntityField": "login",
            "ownerSide": true,
            "otherEntityRelationshipName": "task"
        }
    ],
    "fields": [
        {
            "fieldName": "title",
            "fieldType": "String"
        },
        {
            "fieldName": "description",
            "fieldType": "String"
        }
    ],
    "changelogDate": "20181013072953",
    "dto": "mapstruct",
    "searchEngine": false,
    "service": "serviceImpl",
    "entityTableName": "task",
    "jpaMetamodelFiltering": false,
    "pagination": "no"
}
